{
  "appId": "cc.deltastars.app",
  "appName": "نجوم دلتا | Delta Stars",
  "webDir": "dist",
  "bundledWebRuntime": false,
  "server": {
    "url": "https://deltastars.com",
    "cleartext": true
  },
  "plugins": {
    "SplashScreen": {
      "launchShowDuration": 3000,
      "launchAutoHide": true,
      "backgroundColor": "#1a3a1a",
      "androidSplashResourceName": "splash",
      "androidScaleType": "CENTER_CROP",
      "showSpinner": true,
      "androidSpinnerStyle": "large",
      "iosSpinnerStyle": "small",
      "spinnerColor": "#FF922B",
      "splashFullScreen": true,
      "splashImmersive": true
    },
    "PushNotifications": {
      "presentationOptions": ["badge", "sound", "alert"]
    }
  }
}
